fetch_hackernews/__init__.py
fetch_hackernews/app_config.py
fetch_hackernews/cli_output.py
fetch_hackernews/common.py
fetch_hackernews/data_container.py
fetch_hackernews/data_manager.py
fetch_hackernews/main.py
fetch_hackernews-1.0.8.dist-info/LICENSE
fetch_hackernews-1.0.8.dist-info/METADATA
fetch_hackernews-1.0.8.dist-info/WHEEL
fetch_hackernews-1.0.8.dist-info/entry_points.txt
fetch_hackernews-1.0.8.dist-info/top_level.txt
fetch_hackernews-1.0.8.dist-info/RECORD
