Metadata-Version: 2.2
Name: fetch_hackernews
Version: 1.0.8
Summary: Fetch website data from https://news.ycombinator.com
Home-page: https://github.com/niftycode/fetch_hackernews
Author: Bodo Schönfeld
Author-email: bodo.schoenfeld@niftycode.de
License: MIT
Classifier: Development Status :: 4 - Beta
Classifier: Environment :: Console
Classifier: Intended Audience :: Developers
Classifier: License :: OSI Approved :: MIT License
Classifier: Operating System :: MacOS
Classifier: Operating System :: POSIX :: Linux
Classifier: Operating System :: Microsoft :: Windows
Classifier: Programming Language :: Python :: 3
Classifier: Programming Language :: Python :: 3.12
Classifier: Programming Language :: Python :: 3.13
Classifier: Programming Language :: Python :: Implementation :: CPython
License-File: LICENSE
Requires-Dist: beautifulsoup4
Requires-Dist: requests
Requires-Dist: setuptools
